goldenergy/__init__.py
goldenergy/connection.py
goldenergy/const.py
goldenergy/goldenergy.py
goldenergy/models/__init__.py
goldenergy/models/billing_address.py
goldenergy/models/consumption.py
goldenergy/models/contract.py
goldenergy/models/direct_debit.py
goldenergy/models/electricity.py
goldenergy/models/electricity_product.py
goldenergy/models/electronic_invoice.py
goldenergy/models/gas.py
goldenergy/models/gas_product.py
goldenergy/models/last_invoice.py
goldenergy/models/meter.py
goldenergy/models/payment_owner.py
goldenergy-0.0.2.dist-info/LICENSE
goldenergy-0.0.2.dist-info/METADATA
goldenergy-0.0.2.dist-info/WHEEL
goldenergy-0.0.2.dist-info/top_level.txt
goldenergy-0.0.2.dist-info/RECORD
