Metadata-Version: 2.1
Name: goldenergy
Version: 0.0.2
Summary: Python library to retrieve information from "Goldenergy" client portal
Author-email: Jose Rolo <ze.p.rolo@gmail.com>
License: Apache-2.0
Keywords: api,goldenergy
Classifier: Programming Language :: Python :: 3
Requires-Python: >=3
License-File: LICENSE
Requires-Dist: aiohttp
Requires-Dist: python-dateutil
